MANIFEST.in
README.txt
setup.cfg
setup.py
simplemapplot/BlankMap-World6.css
simplemapplot/BlankMap-World6.svg
simplemapplot/Blank_US_Map.css
simplemapplot/Blank_US_Map.svg
simplemapplot/Usa_counties_large.svg
simplemapplot/__init__.py
simplemapplot/simplemapplot.py
simplemapplot.egg-info/PKG-INFO
simplemapplot.egg-info/SOURCES.txt
simplemapplot.egg-info/dependency_links.txt
simplemapplot.egg-info/top_level.txt