Metadata-Version: 1.1
Name: simplemapplot
Version: 1.0.3
Summary: Simple functions for coloring maps
Home-page: http://pypi.python.org/pypi/simplemapplot/
Author: Michael Anderson
Author-email: mbanderson@uwalumni.com
License: UNKNOWN
Platform: UNKNOWN
Classifier: Development Status :: 5 - Production/Stable
Classifier: Environment :: Console
Classifier: Intended Audience :: Science/Research
Classifier: License :: OSI Approved :: MIT License
Classifier: Natural Language :: English
Classifier: Topic :: Scientific/Engineering :: Visualization
Classifier: Topic :: Utilities
